{
  "phase": 2,
  "phaseLabel": "تفكيك المحطات السبع ومنازلها",
  "title": "الشرح العميق — المرحلة 2: تفكيك المحطات السبع",
  "explanations": [
    {
      "id": "exp-p2-kabaer",
      "concept": "المَحطة الأولى: الكبائر والإسراف في الصَّغائر",
      "explanation": "يبدأ الشَّيطان بالكبائر، فإذا لم تُفْلح انتقل إلى الإسراف في الصَّغائر. الشَّرب والزنا وتَرْك الصلاة، ثُمَّ النَّميمة والكذب بلا داعٍ.",
      "whyItMatters": "هذه الْمَحطة تُفرِّغ الرَّصيد الرُّوحي قبل الانتقال إلى مَحطات أُخرى.",
      "misunderstanding": "الظن أن الكبائر فقط هي الْمَشكلة. الصحيح: إسراف الصَّغائر قد يكون أَعظم خطرًا.",
      "howToApply": "استعمل الـ700 استغفار يوميًا وسَل الله حِفْظ الجوارح.",
      "thinkAboutThis": "ما الصَّغيرة التي يَستهين بها النَّاس ولها أَثَر كبير في قَلْبك؟"
    },
    {
      "id": "exp-p2-ghafla",
      "concept": "المَحطة الثانية: الغَفلة",
      "explanation": "بعد تَرْك الكبائر والِاسْتغفار، يَنقلك الشَّيطان إلى الغَفلة. تَتْرُك الأَمل والهِمَّة، تَكَل وُجودك في الحياة ولا تُريد تَغييرًا.",
      "whyItMatters": "الغَفلة تُبْعدك عن تَلَقِّي الثَّواب.",
      "misunderstanding": "الرِّضا مَعناه الغفلة. الصحيح: الرِّضا إقبال، والغَفلة إدبار.",
      "howToApply": "اِجْعل لِكلِّ يَوم هَدَفًا صَغيرًا.",
      "thinkAboutThis": "ما الذي يُحرِّك ذِهْنك صَباحًا؟ هَل عندك هدف؟"
    },
    {
      "id": "exp-p2-hamm",
      "concept": "المَحطة الثالثة: الْهَمّ",
      "explanation": "الإغراق في الهموم. سَيْر على سَلاسل القلق يَدْأ من فِكرة بَسيطة حتى تَتَحول إلى هَمّ مُستمر. والنَّبي ﷺ سَلاحه التوكُّل، وقَدَّم الدُّعاء «حسبي الله لا إله إلا هو عليه توكَّلت وهو ربُّ العرش العظيم».",
      "whyItMatters": "مِن أَكثر أمْراض العصر، ويُسقط فاعلية الإنسان.",
      "misunderstanding": "التَّفكير المُستمر حلٌّ. الصحيح: التَّفكير المُفرط هَرَب.",
      "howToApply": "ضَع قُيودًا على التَّفكير، ثُمَّ تَعوَّد على سَبْع «حسبي الله» صباحًا.",
      "thinkAboutThis": "كم سَاعة ضَيَّعتَ في هَمّ لم يَتَحقق؟"
    },
    {
      "id": "exp-p2-yas",
      "concept": "المَحطة الرابعة: اليأس عند المصائب",
      "explanation": "في الْمَصائب يَستدرجك الشَّيطان لليأس مِن رَحمة الله. سُلاحك: التَّسليم. «لا حَول ولا قُوَّة إلا بالله». والتَّسليم لا يُلغي المعاناة لكنه يُخفضها إلى الحَدّ الأدنى.",
      "whyItMatters": "اليأس يُسقط الدَّافِع، والتَّسليم يُحافظ على فاعلية الإنسان في الْمَصيبة.",
      "misunderstanding": "اليأس مَعناه الإحساس. الصحيح: الإحساس مَعه تَسليم.",
      "howToApply": "حين تَأتيك مَصيبة، ابدأ بِـ«لا حَول ولا قُوَّة إلا بالله» ثلاثين مرَّة.",
      "thinkAboutThis": "ما الْمَصيبة التي أَيأستَك قبل التَّسليم؟"
    },
    {
      "id": "exp-p2-tama",
      "concept": "المَحطة الخامسة: الطَّمع",
      "explanation": "الطَّمع جُنُون العَين: تَرَى ما في يَد غيرك أَحْلى مِمَّا في يَدك.",
      "whyItMatters": "في عَصر السُّوشيال ميديا، الْمُقارنة سَرْعة في تَحطيمك النَّفسي.",
      "misunderstanding": "الرِّضا مَعناه الكسل. الصحيح: الرِّضا عَمَل قَلْبي، والدُّعاء مَشروع.",
      "howToApply": "حين تَفتح سُوشيال ميديا، قُل «رَبِّ اشمعني أنا؟ الحمد لله».",
      "thinkAboutThis": "أيُّ صُورة أَثَّرت فيك آخر الأسبُوع؟ لِمَ؟"
    },
    {
      "id": "exp-p2-shape-jawhar",
      "concept": "المَحطة السادسة: تَشغِيلك بالشَّكل عن الجَوهر",
      "explanation": "يُشغِلك الشَّيطان بالأَقَل أَهمِّية (شَكل الحجاب مثلًا) عن الأكثَر أَهمِّية (الأَخلاق). حديث «الإيمان بِضْع وسبعون شُعْبة أَعْلاها لا إله إلا الله وأَدْناها إماطة الأَذَى عن الطَّريق».",
      "whyItMatters": "الْجَوْهر أَهم من الشَّكل، لكن يَنْسى الْمُسلمون ذلك في حِرْصهم على المُظْهر.",
      "misunderstanding": "الإسلام يتَطلب تَفاصيل صَغيرة. الصَّحيح: الإسلام يَتطلب قَلْبًا مَع الحياة.",
      "howToApply": "حين يَفرض أحدٌ عليك تَفصيلًا شَكليًّا، سَل: ما الجَوهر الذي يَرِيده الله؟",
      "thinkAboutThis": "أَيُّ خِلاف يومي يَدور على الشَّكل لا الجَوهر؟"
    },
    {
      "id": "exp-p2-taslih",
      "concept": "المَحطة السابعة: تَسليحك بالمعاصي",
      "explanation": "يُسلِّحك الشَّيطان بصَغائر تَتْراكم حتى تُؤخِّرك عن الفردوس الأَعلى. سِلاحك: الاستعاذة والدُّعاء.",
      "whyItMatters": "الصَّغائر المُتراكمة تُسقط الشَّخص من العُلُوّ.",
      "misunderstanding": "الظن أن الْمَحطات مَنفصلة. الصَّحيح: سَيْر الشَّيطان مُستمر، وباب الِانْكِسار مفتوح.",
      "howToApply": "اِدْعُ كلَّ صَباح: «اللهم إني أَعُوذ بك من شر سمعي ... ومن شر مَنِيّي».",
      "thinkAboutThis": "أَيُّ صغيرة تُلازِمك وتُسقطك من أعالي الدَّرَجة؟"
    }
  ]
}
